OBITools3-3.0.1b1.data/scripts/obi
obitools3/__init__.py
obitools3/utils.cpython-37m-darwin.so
obitools3/version.py
obitools3/apps/__init__.py
obitools3/apps/arguments.cpython-37m-darwin.so
obitools3/apps/command.cpython-37m-darwin.so
obitools3/apps/config.cpython-37m-darwin.so
obitools3/apps/logging.cpython-37m-darwin.so
obitools3/apps/progress.cpython-37m-darwin.so
obitools3/apps/temp.cpython-37m-darwin.so
obitools3/apps/arguments.cpython-37m-darwin.so.dSYM/Contents/Info.plist
obitools3/apps/arguments.cpython-37m-darwin.so.dSYM/Contents/Resources/DWARF/arguments.cpython-37m-darwin.so
obitools3/apps/command.cpython-37m-darwin.so.dSYM/Contents/Info.plist
obitools3/apps/command.cpython-37m-darwin.so.dSYM/Contents/Resources/DWARF/command.cpython-37m-darwin.so
obitools3/apps/config.cpython-37m-darwin.so.dSYM/Contents/Info.plist
obitools3/apps/config.cpython-37m-darwin.so.dSYM/Contents/Resources/DWARF/config.cpython-37m-darwin.so
obitools3/apps/logging.cpython-37m-darwin.so.dSYM/Contents/Info.plist
obitools3/apps/logging.cpython-37m-darwin.so.dSYM/Contents/Resources/DWARF/logging.cpython-37m-darwin.so
obitools3/apps/optiongroups/__init__.py
obitools3/apps/progress.cpython-37m-darwin.so.dSYM/Contents/Info.plist
obitools3/apps/progress.cpython-37m-darwin.so.dSYM/Contents/Resources/DWARF/progress.cpython-37m-darwin.so
obitools3/apps/temp.cpython-37m-darwin.so.dSYM/Contents/Info.plist
obitools3/apps/temp.cpython-37m-darwin.so.dSYM/Contents/Resources/DWARF/temp.cpython-37m-darwin.so
obitools3/commands/__init__.py
obitools3/commands/addtaxids.cpython-37m-darwin.so
obitools3/commands/align.cpython-37m-darwin.so
obitools3/commands/alignpairedend.cpython-37m-darwin.so
obitools3/commands/annotate.cpython-37m-darwin.so
obitools3/commands/build_ref_db.cpython-37m-darwin.so
obitools3/commands/cat.cpython-37m-darwin.so
obitools3/commands/clean.cpython-37m-darwin.so
obitools3/commands/clean_dms.cpython-37m-darwin.so
obitools3/commands/count.cpython-37m-darwin.so
OBITools3-3.0.1b1.dist-info/LICENSE
OBITools3-3.0.1b1.dist-info/METADATA
OBITools3-3.0.1b1.dist-info/WHEEL
OBITools3-3.0.1b1.dist-info/top_level.txt
OBITools3-3.0.1b1.dist-info/RECORD
