Metadata-Version: 2.1
Name: OBITools3
Version: 3.0.1b1
Summary: A package for the management of analyses and data in DNA metabarcoding.
Home-page: https://metabarcoding.org/obitools3
Author: Celine Mercier
Author-email: celine.mercier@metabarcoding.org
License: CeCILL-V2
Platform: posix
Classifier: Development Status :: 4 - Beta
Classifier: Environment :: Console
Classifier: Intended Audience :: Science/Research
Classifier: License :: Other/Proprietary License
Classifier: Operating System :: Unix
Classifier: Programming Language :: Python :: 3
Classifier: Programming Language :: C
Classifier: Topic :: Scientific/Engineering :: Bio-Informatics
Classifier: Topic :: Utilities
